{
  "cookies": [
    {
      "name": "wp_wpfileupload_bcee46caf8128c4169fb42a56c1b36e7",
      "value": "XtLnjOH2qnLHCDAqe75npmLLNkk1qg5g",
      "domain": "practice.sdetunicorns.com",
      "path": "/",
      "expires": 1699379465.071453,
      "httpOnly": false,
      "secure": true,
      "sameSite": "Lax"
    },
    {
      "name": "tk_or",
      "value": "%22%22",
      "domain": ".sdetunicorns.com",
      "path": "/",
      "expires": 1733766666.413422,
      "httpOnly": false,
      "secure": false,
      "sameSite": "Lax"
    },
    {
      "name": "tk_r3d",
      "value": "%22%22",
      "domain": ".sdetunicorns.com",
      "path": "/",
      "expires": 1699465866,
      "httpOnly": false,
      "secure": false,
      "sameSite": "Lax"
    },
    {
      "name": "tk_lr",
      "value": "%22%22",
      "domain": ".sdetunicorns.com",
      "path": "/",
      "expires": 1730742666,
      "httpOnly": false,
      "secure": false,
      "sameSite": "Lax"
    }
  ],
  "origins": []
}